README.md
setup.cfg
setup.py
src/montapy/http_api/__init__.py
src/montapy_http_api.egg-info/PKG-INFO
src/montapy_http_api.egg-info/SOURCES.txt
src/montapy_http_api.egg-info/dependency_links.txt
src/montapy_http_api.egg-info/requires.txt
src/montapy_http_api.egg-info/top_level.txt