Metadata-Version: 2.1
Name: montapy-http-api
Version: 0.1.0
Summary: Repository and entities for building HTTP API's clients
Home-page: https://github.com/montapy/http-api
Author: Sergey Volkov
Author-email: volkov.sergey.e@gmail.com
License: MIT
Project-URL: CI: Travis, https://travis-ci.com/montapy/http-api
Project-URL: GitHub: issues, https://github.com/montapy/http-api/issues
Project-URL: GitHub: repo, https://github.com/montapy/http-api
Platform: UNKNOWN
Classifier: Development Status :: 2 - Pre-Alpha
Classifier: Intended Audience :: Developers
Classifier: Framework :: AsyncIO
Classifier: License :: OSI Approved :: MIT License
Classifier: Programming Language :: Python
Classifier: Programming Language :: Python :: 3
Classifier: Programming Language :: Python :: 3.7
Classifier: Programming Language :: Python :: 3.8
Classifier: Programming Language :: Python :: 3.9
Classifier: Topic :: Software Development
Classifier: Topic :: Utilities
Provides-Extra: dev
Provides-Extra: test
